patchdiff/__init__.py
patchdiff/apply.py
patchdiff/diff.py
patchdiff/pointer.py
patchdiff/serialize.py
patchdiff/types.py
patchdiff-0.3.7.dist-info/METADATA
patchdiff-0.3.7.dist-info/WHEEL
patchdiff-0.3.7.dist-info/RECORD
