Metadata-Version: 2.4
Name: patchdiff
Version: 0.3.7
Summary: MIT
Project-URL: Homepage, https://github.com/fork-tongue/patchdiff
Author-email: Korijn van Golen <korijn@gmail.com>, Berend Klein Haneveld <berendkleinhaneveld@gmail.com>
Requires-Python: >=3.8
